<annotation>
    <folder>tomates</folder>
    <filename>tomates_2020-08-06-11-35-15_side_0102.jpg</filename>
    <path>/home/tiago/Desktop/INESCTEC/DadosDataset/Dataset_test/Tomato_dataset_test_split/JPEGImages/tomates_2020-08-06-11-35-15_side_0102_01.jpg</path>
    <source>
        <database>Unknown</database>
    </source>
    <size>
        <width>720</width>
        <height>720</height>
        <depth>None</depth>
    </size>
    <segmented>0</segmented>
    <object>
        <name>Tomato</name>
        <pose>Unspecified</pose>
        <truncated>0</truncated>
        <difficult>0</difficult>
        <bndbox>
            <xmin>488</xmin>
            <ymin>426</ymin>
            <xmax>547</xmax>
            <ymax>511</ymax>
        </bndbox>
    </object>
    <object>
        <name>Tomato</name>
        <pose>Unspecified</pose>
        <truncated>0</truncated>
        <difficult>0</difficult>
        <bndbox>
            <xmin>350</xmin>
            <ymin>287</ymin>
            <xmax>445</xmax>
            <ymax>417</ymax>
        </bndbox>
    </object>
    <object>
        <name>Tomato</name>
        <pose>Unspecified</pose>
        <truncated>0</truncated>
        <difficult>0</difficult>
        <bndbox>
            <xmin>404</xmin>
            <ymin>350</ymin>
            <xmax>491</xmax>
            <ymax>460</ymax>
        </bndbox>
    </object>
    <object>
        <name>Tomato</name>
        <pose>Unspecified</pose>
        <truncated>0</truncated>
        <difficult>0</difficult>
        <bndbox>
            <xmin>455</xmin>
            <ymin>322</ymin>
            <xmax>520</xmax>
            <ymax>402</ymax>
        </bndbox>
    </object>
    <object>
        <name>Tomato</name>
        <pose>Unspecified</pose>
        <truncated>0</truncated>
        <difficult>0</difficult>
        <bndbox>
            <xmin>531</xmin>
            <ymin>416</ymin>
            <xmax>577</xmax>
            <ymax>477</ymax>
        </bndbox>
    </object>
    <object>
        <name>Tomato</name>
        <pose>Unspecified</pose>
        <truncated>0</truncated>
        <difficult>0</difficult>
        <bndbox>
            <xmin>492</xmin>
            <ymin>390</ymin>
            <xmax>551</xmax>
            <ymax>461</ymax>
        </bndbox>
    </object>
    <object>
        <name>Tomato</name>
        <pose>Unspecified</pose>
        <truncated>0</truncated>
        <difficult>0</difficult>
        <bndbox>
            <xmin>380</xmin>
            <ymin>182</ymin>
            <xmax>441</xmax>
            <ymax>263</ymax>
        </bndbox>
    </object>
    <object>
        <name>Tomato</name>
        <pose>Unspecified</pose>
        <truncated>0</truncated>
        <difficult>0</difficult>
        <bndbox>
            <xmin>345</xmin>
            <ymin>74</ymin>
            <xmax>418</xmax>
            <ymax>164</ymax>
        </bndbox>
    </object>
    <object>
        <name>Tomato</name>
        <pose>Unspecified</pose>
        <truncated>0</truncated>
        <difficult>0</difficult>
        <bndbox>
            <xmin>354</xmin>
            <ymin>126</ymin>
            <xmax>434</xmax>
            <ymax>209</ymax>
        </bndbox>
    </object>
</annotation>
